{
    "imageUrl": "{{TMP_SERVER_URL}}/msa/api/images/checkup/nails.jpg",
    "title": {
        "description": "Программа обследования",
        "header": "Крепкие ногти"
    },
    "items": [
        {
            "description": "Материал для анализов",
            "header": "Кровь и Ногти",
            "iconUrl": "{{TMP_SERVER_URL}}/msa/api/images/cosm/icons/materialsImg.png"
        },
        {
            "description": "Срок готовности анализов",
            "header": "До 23 рабочих дней",
            "iconUrl": "{{TMP_SERVER_URL}}/msa/api/images/cosm/icons/dateImg.png"
        }
    ],
    "descriptionButton": {
        "name": "Как подготовиться к сдаче анализов",
        "descriptionContent": {
            "title": "Как подготовиться к сдаче анализов",
            "blocks": [
                {
                    "title": "Общий анализ крови",
                    "description": "Сдача крови происходит натощак, прием пищи необходимо исключить минимум за 8 часов до сдачи анализа. Накануне исследования рекомендуется ограничить повышенные психоэмоциональные и физические нагрузки (спортивные тренировки), интимную близость, тепловые воздействия (сауну), приём алкоголя, за час до исследования – курение. Желательно находиться в покое 20-30 мин. перед взятием крови.",
                    "items": []
                },
                {
                    "title": "В обследование входят следующие лабораторные тесты:",
                    "items": [
                        "Микроскопическое исследование ногтевых пластинок на наличие патогенных грибов",
                        "Посев на грибы",
                        "ОАК",
                        "Лейкоцитарная формула",
                        "Общий анализ мочи",
                        "Глюкоза крови",
                        "Витамин Д"
                    ]
                }
            ]
        }
    },
    "nextButton": {
        "name": "Записаться в лабораторию"
    },
    "description": "Комплексное лабораторное обследования организма, направленное на выявление причин проблем с ногтями.\nПо результатам обследования вы получите:\n- Диагностику причин появления проблем с ногтями\n- Экспертную консультацию врача-косметолога\n- Описание проведенных исследований и расшифровку результатов анализов"
}